str2bool3/__init__.py
str2bool3/str_utils.py
str2bool3-1.3.0.dist-info/LICENSE
str2bool3-1.3.0.dist-info/METADATA
str2bool3-1.3.0.dist-info/WHEEL
str2bool3-1.3.0.dist-info/top_level.txt
str2bool3-1.3.0.dist-info/RECORD
