Metadata-Version: 2.1
Name: str2bool3
Version: 1.3.0
Summary: Convert string to boolean (Forked from SymonSoft/str2bool)
Home-page: https://github.com/sam-fakhreddine/str2bool3
Download-URL: https://github.com/sam-fakhreddine/str2bool3/archive/refs/tags/1.3.0.tar.gz
Author: Sam Fakhreddine
Author-email: sam.fakhreddine@gmail.com
Keywords: str2bool,bool,boolean,convert,yes,no,true,false
Classifier: Development Status :: 5 - Production/Stable
Classifier: License :: OSI Approved :: BSD License
Classifier: Operating System :: OS Independent
Classifier: Programming Language :: Python :: 3.8
Classifier: Programming Language :: Python :: 3.9
Classifier: Programming Language :: Python :: 3.10
Classifier: Programming Language :: Python :: 3.11
Classifier: Programming Language :: Python :: 3.12
Classifier: Topic :: Utilities
License-File: LICENSE
